nvhtop/__init__.py
nvhtop/commands.py
nvhtop/htop.py
nvhtop/nvidia_smi.py
nvhtop/process.py
nvhtop/ps.py
nvhtop/run.py
nvhtop/tests/__init__.py
nvhtop/tests/htop_tests.py
nvhtop/tests/nvidia_smi_test.py
nvhtop/tests/ps_test.py
nvhtop/tests/test_case.py
nvhtop/tests/util.py
nvhtop/util/__init__.py
nvhtop/util/colorize.py
nvhtop-0.1.dist-info/LICENSE
nvhtop-0.1.dist-info/METADATA
nvhtop-0.1.dist-info/WHEEL
nvhtop-0.1.dist-info/entry_points.txt
nvhtop-0.1.dist-info/top_level.txt
nvhtop-0.1.dist-info/RECORD
