Metadata-Version: 2.1
Name: nvhtop
Version: 0.1
Summary: A tool for enriching the output of nvidia-smi
Home-page: https://github.com/shunk031/nvhtop
Author: Shunsuke Kitada
Author-email: shunsuke.kitada.0831@gmail.com
License: UNKNOWN
Platform: UNKNOWN
Classifier: Programming Language :: Python :: 3.7
Classifier: License :: OSI Approved :: MIT License
Classifier: Operating System :: OS Independent
Requires-Python: >=3.7
Requires-Dist: termcolor
